abstract_distances/__init__.py
abstract_distances/char_compar.py
abstract_distances/distance_cals.py
abstract_distances/do_distance.py
abstract_distances/excel_module.py
abstract_distances/functions.py
abstract_distances/geo_pandas.py
abstract_distances/geo_spec.py
abstract_distances/get_conversion.py
abstract_distances/get_zz.py
abstract_distances/test.py
abstract_distances/word_compare.py
abstract_distances-0.0.0.11.dist-info/METADATA
abstract_distances-0.0.0.11.dist-info/WHEEL
abstract_distances-0.0.0.11.dist-info/top_level.txt
abstract_distances-0.0.0.11.dist-info/RECORD
