Metadata-Version: 2.1
Name: abstract_distances
Version: 0.0.0.11
Author: putkoff
Author-email: partners@abstractendeavors.com
Classifier: Development Status :: 3 - Alpha
Classifier: Intended Audience :: Developers
Classifier: License :: OSI Approved :: MIT License
Classifier: Programming Language :: Python :: 3
Classifier: Programming Language :: Python :: 3.11
Requires-Python: >=3.6
Requires-Dist: abstract-utilities
Requires-Dist: abstract-security
Requires-Dist: abstract-pandas
Requires-Dist: requests
Requires-Dist: openlocationcode
Requires-Dist: numpy
